StatPayer/app.py
StatPayer/engine.py
statpayer-1.0.2.dist-info/METADATA
statpayer-1.0.2.dist-info/WHEEL
statpayer-1.0.2.dist-info/entry_points.txt
statpayer-1.0.2.dist-info/top_level.txt
statpayer-1.0.2.dist-info/RECORD
