Metadata-Version: 2.4
Name: StatPayer
Version: 1.0.2
Summary: Not developed in Switzerland, but developed in St. Martin (French Side)
Author-email: "Davis V. Garrad" <davis.garrad@gmail.com>
License-Expression: GPL-3.0-only
Project-URL: Homepage, https://github.com/Davis-Garrad/StatPayer
Project-URL: Issues, https://github.com/Davis-Garrad/StatPayer/issues
Classifier: Programming Language :: Python :: 3
Classifier: Operating System :: OS Independent
Requires-Python: >=3.9
Requires-Dist: PyQt6
Requires-Dist: pandas
